stonfisdk/__init__.py
stonfisdk/constants.py
stonfisdk/utils.py
stonfisdk/contracts/__init__.py
stonfisdk/contracts/dex/__init__.py
stonfisdk/contracts/dex/v1/__init__.py
stonfisdk/contracts/dex/v1/lp_account.py
stonfisdk/contracts/dex/v1/pool.py
stonfisdk/contracts/dex/v1/router.py
stonfisdk/contracts/farm/__init__.py
stonfisdk/contracts/jetton/__init__.py
stonfisdk/contracts/jetton/jetton_root.py
stonfisdk/contracts/jetton/jetton_wallet.py
stonfisdk/contracts/pTON/__init__.py
stonfisdk/contracts/pTON/v1.py
stonfisdk/http/__init__.py
stonfisdk/http/api_client.py
stonfisdk/types/__init__.py
stonfisdk/types/http/__init__.py
stonfisdk/types/http/assets.py
stonfisdk/types/http/farms.py
stonfisdk/types/http/pools.py
stonfisdk/types/http/swap.py
stonfisdk-0.0.1.dist-info/LICENSE
stonfisdk-0.0.1.dist-info/METADATA
stonfisdk-0.0.1.dist-info/WHEEL
stonfisdk-0.0.1.dist-info/top_level.txt
stonfisdk-0.0.1.dist-info/RECORD
